meru/__init__.py
meru/actions.py
meru/exceptions.py
meru/handlers.py
meru/helpers.py
meru/serialization.py
meru/sockets.py
meru/state.py
meru-0.2.1.dist-info/LICENSE
meru-0.2.1.dist-info/METADATA
meru-0.2.1.dist-info/WHEEL
meru-0.2.1.dist-info/top_level.txt
meru-0.2.1.dist-info/zip-safe
meru-0.2.1.dist-info/RECORD
